{
 "custom_fields": [
  {
   "_assign": null,
   "_comments": null,
   "_liked_by": null,
   "_user_tags": null,
   "allow_in_quick_entry": 0,
   "allow_on_submit": 0,
   "bold": 0,
   "collapsible": 0,
   "collapsible_depends_on": null,
   "columns": 0,
   "creation": "2022-07-25 13:03:35.844531",
   "default": null,
   "depends_on": null,
   "description": null,
   "docstatus": 0,
   "dt": "Purchase Invoice",
   "fetch_from": null,
   "fetch_if_empty": 0,
   "fieldname": "business_unit",
   "fieldtype": "Link",
   "hidden": 0,
   "idx": 22,
   "ignore_user_permissions": 0,
   "ignore_xss_filter": 0,
   "in_global_search": 0,
   "in_list_view": 0,
   "in_standard_filter": 0,
   "insert_after": "department",
   "label": "Business Unit",
   "length": 0,
   "modified": "2020-08-21 18:22:48.460133",
   "modified_by": "Administrator",
   "name": "Purchase Invoice-business_unit",
   "no_copy": 0,
   "options": "Business Unit",
   "owner": "Administrator",
   "parent": null,
   "parentfield": null,
   "parenttype": null,
   "permlevel": 0,
   "precision": "",
   "print_hide": 0,
   "print_hide_if_no_value": 0,
   "print_width": null,
   "read_only": 0,
   "report_hide": 0,
   "reqd": 0,
   "search_index": 0,
   "translatable": 0,
   "unique": 0,
   "width": null
  },
  {
   "_assign": null,
   "_comments": null,
   "_liked_by": null,
   "_user_tags": null,
   "allow_in_quick_entry": 0,
   "allow_on_submit": 0,
   "bold": 0,
   "collapsible": 0,
   "collapsible_depends_on": null,
   "columns": 0,
   "creation": "2022-07-25 13:03:33.092531",
   "default": null,
   "depends_on": null,
   "description": null,
   "docstatus": 0,
   "dt": "Purchase Invoice",
   "fetch_from": null,
   "fetch_if_empty": 0,
   "fieldname": "department",
   "fieldtype": "Link",
   "hidden": 0,
   "idx": 21,
   "ignore_user_permissions": 0,
   "ignore_xss_filter": 0,
   "in_global_search": 0,
   "in_list_view": 0,
   "in_standard_filter": 0,
   "insert_after": "accounting_dimensions_section",
   "label": "Department",
   "length": 0,
   "modified": "2020-08-21 18:48:51.157870",
   "modified_by": "Administrator",
   "name": "Purchase Invoice-department",
   "no_copy": 0,
   "options": "Department",
   "owner": "Administrator",
   "parent": null,
   "parentfield": null,
   "parenttype": null,
   "permlevel": 0,
   "precision": "",
   "print_hide": 0,
   "print_hide_if_no_value": 0,
   "print_width": null,
   "read_only": 0,
   "report_hide": 0,
   "reqd": 0,
   "search_index": 0,
   "translatable": 0,
   "unique": 0,
   "width": null
  },
  {
   "_assign": null,
   "_comments": null,
   "_liked_by": null,
   "_user_tags": null,
   "allow_in_quick_entry": 0,
   "allow_on_submit": 0,
   "bold": 0,
   "collapsible": 0,
   "collapsible_depends_on": null,
   "columns": 0,
   "creation": "2022-07-25 13:03:06.973740",
   "default": null,
   "depends_on": "",
   "description": null,
   "docstatus": 0,
   "dt": "Purchase Invoice",
   "fetch_from": null,
   "fetch_if_empty": 0,
   "fieldname": "supplier_reference",
   "fieldtype": "Data",
   "hidden": 0,
   "idx": 17,
   "ignore_user_permissions": 0,
   "ignore_xss_filter": 0,
   "in_global_search": 0,
   "in_list_view": 0,
   "in_standard_filter": 0,
   "insert_after": "gate_pass",
   "label": "Supplier Reference",
   "length": 0,
   "modified": "2021-06-09 14:19:32.832119",
   "modified_by": "Administrator",
   "name": "Purchase Invoice-supplier_reference",
   "no_copy": 0,
   "options": null,
   "owner": "Administrator",
   "parent": null,
   "parentfield": null,
   "parenttype": null,
   "permlevel": 0,
   "precision": "",
   "print_hide": 0,
   "print_hide_if_no_value": 0,
   "print_width": null,
   "read_only": 0,
   "report_hide": 0,
   "reqd": 0,
   "search_index": 0,
   "translatable": 0,
   "unique": 0,
   "width": null
  },
  {
   "_assign": null,
   "_comments": null,
   "_liked_by": null,
   "_user_tags": null,
   "allow_in_quick_entry": 0,
   "allow_on_submit": 1,
   "bold": 0,
   "collapsible": 0,
   "collapsible_depends_on": null,
   "columns": 0,
   "creation": "2022-07-25 13:00:58.602290",
   "default": null,
   "depends_on": null,
   "description": null,
   "docstatus": 0,
   "dt": "Purchase Invoice",
   "fetch_from": null,
   "fetch_if_empty": 0,
   "fieldname": "workflow_state",
   "fieldtype": "Link",
   "hidden": 1,
   "idx": 1,
   "ignore_user_permissions": 0,
   "ignore_xss_filter": 0,
   "in_global_search": 0,
   "in_list_view": 0,
   "in_standard_filter": 0,
   "insert_after": null,
   "label": "Workflow State",
   "length": 0,
   "modified": "2021-08-18 12:33:31.719232",
   "modified_by": "Administrator",
   "name": "Purchase Invoice-workflow_state",
   "no_copy": 1,
   "options": "Workflow State",
   "owner": "Administrator",
   "parent": null,
   "parentfield": null,
   "parenttype": null,
   "permlevel": 0,
   "precision": "",
   "print_hide": 0,
   "print_hide_if_no_value": 0,
   "print_width": null,
   "read_only": 0,
   "report_hide": 0,
   "reqd": 0,
   "search_index": 0,
   "translatable": 0,
   "unique": 0,
   "width": null
  },
  {
   "_assign": null,
   "_comments": null,
   "_liked_by": null,
   "_user_tags": null,
   "allow_in_quick_entry": 0,
   "allow_on_submit": 0,
   "bold": 0,
   "collapsible": 0,
   "collapsible_depends_on": null,
   "columns": 0,
   "creation": "2022-07-25 13:03:01.542881",
   "default": null,
   "depends_on": null,
   "description": null,
   "docstatus": 0,
   "dt": "Purchase Invoice",
   "fetch_from": null,
   "fetch_if_empty": 0,
   "fieldname": "gate_pass",
   "fieldtype": "Link",
   "hidden": 0,
   "idx": 16,
   "ignore_user_permissions": 0,
   "ignore_xss_filter": 0,
   "in_global_search": 0,
   "in_list_view": 0,
   "in_standard_filter": 0,
   "insert_after": "posting_time",
   "label": "Gate Pass",
   "length": 0,
   "modified": "2021-10-21 15:49:49.762057",
   "modified_by": "Administrator",
   "name": "Purchase Invoice-gate_pass",
   "no_copy": 0,
   "options": "Gate Pass",
   "owner": "Administrator",
   "parent": null,
   "parentfield": null,
   "parenttype": null,
   "permlevel": 0,
   "precision": "",
   "print_hide": 0,
   "print_hide_if_no_value": 0,
   "print_width": null,
   "read_only": 0,
   "report_hide": 0,
   "reqd": 1,
   "search_index": 0,
   "translatable": 0,
   "unique": 0,
   "width": null
  },
  {
   "_assign": null,
   "_comments": null,
   "_liked_by": null,
   "_user_tags": null,
   "allow_in_quick_entry": 0,
   "allow_on_submit": 0,
   "bold": 0,
   "collapsible": 0,
   "collapsible_depends_on": null,
   "columns": 0,
   "creation": "2022-07-25 13:04:57.049473",
   "default": null,
   "depends_on": null,
   "description": null,
   "docstatus": 0,
   "dt": "Purchase Invoice",
   "fetch_from": null,
   "fetch_if_empty": 0,
   "fieldname": "transporter_details",
   "fieldtype": "Section Break",
   "hidden": 0,
   "idx": 159,
   "ignore_user_permissions": 0,
   "ignore_xss_filter": 0,
   "in_global_search": 0,
   "in_list_view": 0,
   "in_standard_filter": 0,
   "insert_after": "update_auto_repeat_reference",
   "label": "Transporter Details",
   "length": 0,
   "modified": "2021-10-21 15:57:18.341760",
   "modified_by": "Administrator",
   "name": "Purchase Invoice-transporter_details",
   "no_copy": 0,
   "options": null,
   "owner": "Administrator",
   "parent": null,
   "parentfield": null,
   "parenttype": null,
   "permlevel": 0,
   "precision": "",
   "print_hide": 0,
   "print_hide_if_no_value": 0,
   "print_width": null,
   "read_only": 0,
   "report_hide": 0,
   "reqd": 0,
   "search_index": 0,
   "translatable": 0,
   "unique": 0,
   "width": null
  },
  {
   "_assign": null,
   "_comments": null,
   "_liked_by": null,
   "_user_tags": null,
   "allow_in_quick_entry": 0,
   "allow_on_submit": 0,
   "bold": 0,
   "collapsible": 0,
   "collapsible_depends_on": null,
   "columns": 0,
   "creation": "2022-07-25 13:04:57.990771",
   "default": null,
   "depends_on": null,
   "description": null,
   "docstatus": 0,
   "dt": "Purchase Invoice",
   "fetch_from": null,
   "fetch_if_empty": 0,
   "fieldname": "vehicle_number",
   "fieldtype": "Data",
   "hidden": 0,
   "idx": 160,
   "ignore_user_permissions": 0,
   "ignore_xss_filter": 0,
   "in_global_search": 0,
   "in_list_view": 0,
   "in_standard_filter": 0,
   "insert_after": "transporter_details",
   "label": "Vehicle Number",
   "length": 0,
   "modified": "2021-10-21 15:57:19.149253",
   "modified_by": "Administrator",
   "name": "Purchase Invoice-vehicle_number",
   "no_copy": 0,
   "options": null,
   "owner": "Administrator",
   "parent": null,
   "parentfield": null,
   "parenttype": null,
   "permlevel": 0,
   "precision": "",
   "print_hide": 0,
   "print_hide_if_no_value": 0,
   "print_width": null,
   "read_only": 1,
   "report_hide": 0,
   "reqd": 0,
   "search_index": 0,
   "translatable": 0,
   "unique": 0,
   "width": null
  },
  {
   "_assign": null,
   "_comments": null,
   "_liked_by": null,
   "_user_tags": null,
   "allow_in_quick_entry": 0,
   "allow_on_submit": 0,
   "bold": 0,
   "collapsible": 0,
   "collapsible_depends_on": null,
   "columns": 0,
   "creation": "2022-07-25 13:04:58.841503",
   "default": null,
   "depends_on": null,
   "description": null,
   "docstatus": 0,
   "dt": "Purchase Invoice",
   "fetch_from": null,
   "fetch_if_empty": 0,
   "fieldname": "token_no",
   "fieldtype": "Data",
   "hidden": 0,
   "idx": 161,
   "ignore_user_permissions": 0,
   "ignore_xss_filter": 0,
   "in_global_search": 0,
   "in_list_view": 0,
   "in_standard_filter": 0,
   "insert_after": "vehicle_number",
   "label": "Token No",
   "length": 0,
   "modified": "2021-10-21 15:57:20.457737",
   "modified_by": "Administrator",
   "name": "Purchase Invoice-token_no",
   "no_copy": 0,
   "options": null,
   "owner": "Administrator",
   "parent": null,
   "parentfield": null,
   "parenttype": null,
   "permlevel": 0,
   "precision": "",
   "print_hide": 0,
   "print_hide_if_no_value": 0,
   "print_width": null,
   "read_only": 1,
   "report_hide": 0,
   "reqd": 0,
   "search_index": 0,
   "translatable": 0,
   "unique": 0,
   "width": null
  },
  {
   "_assign": null,
   "_comments": null,
   "_liked_by": null,
   "_user_tags": null,
   "allow_in_quick_entry": 0,
   "allow_on_submit": 0,
   "bold": 0,
   "collapsible": 0,
   "collapsible_depends_on": null,
   "columns": 0,
   "creation": "2022-07-25 13:04:59.950228",
   "default": null,
   "depends_on": null,
   "description": null,
   "docstatus": 0,
   "dt": "Purchase Invoice",
   "fetch_from": null,
   "fetch_if_empty": 0,
   "fieldname": "permit_no",
   "fieldtype": "Data",
   "hidden": 0,
   "idx": 162,
   "ignore_user_permissions": 0,
   "ignore_xss_filter": 0,
   "in_global_search": 0,
   "in_list_view": 0,
   "in_standard_filter": 0,
   "insert_after": "token_no",
   "label": "Permit No",
   "length": 0,
   "modified": "2021-10-21 15:57:21.989722",
   "modified_by": "Administrator",
   "name": "Purchase Invoice-permit_no",
   "no_copy": 0,
   "options": null,
   "owner": "Administrator",
   "parent": null,
   "parentfield": null,
   "parenttype": null,
   "permlevel": 0,
   "precision": "",
   "print_hide": 0,
   "print_hide_if_no_value": 0,
   "print_width": null,
   "read_only": 1,
   "report_hide": 0,
   "reqd": 0,
   "search_index": 0,
   "translatable": 0,
   "unique": 0,
   "width": null
  },
  {
   "_assign": null,
   "_comments": null,
   "_liked_by": null,
   "_user_tags": null,
   "allow_in_quick_entry": 0,
   "allow_on_submit": 0,
   "bold": 0,
   "collapsible": 0,
   "collapsible_depends_on": null,
   "columns": 0,
   "creation": "2022-07-25 13:05:00.938968",
   "default": null,
   "depends_on": null,
   "description": null,
   "docstatus": 0,
   "dt": "Purchase Invoice",
   "fetch_from": null,
   "fetch_if_empty": 0,
   "fieldname": "column_break_159",
   "fieldtype": "Column Break",
   "hidden": 0,
   "idx": 163,
   "ignore_user_permissions": 0,
   "ignore_xss_filter": 0,
   "in_global_search": 0,
   "in_list_view": 0,
   "in_standard_filter": 0,
   "insert_after": "permit_no",
   "label": null,
   "length": 0,
   "modified": "2021-10-21 15:57:23.249566",
   "modified_by": "Administrator",
   "name": "Purchase Invoice-column_break_159",
   "no_copy": 0,
   "options": null,
   "owner": "Administrator",
   "parent": null,
   "parentfield": null,
   "parenttype": null,
   "permlevel": 0,
   "precision": "",
   "print_hide": 0,
   "print_hide_if_no_value": 0,
   "print_width": null,
   "read_only": 0,
   "report_hide": 0,
   "reqd": 0,
   "search_index": 0,
   "translatable": 0,
   "unique": 0,
   "width": null
  },
  {
   "_assign": null,
   "_comments": null,
   "_liked_by": null,
   "_user_tags": null,
   "allow_in_quick_entry": 0,
   "allow_on_submit": 0,
   "bold": 0,
   "collapsible": 0,
   "collapsible_depends_on": null,
   "columns": 0,
   "creation": "2022-07-25 13:05:07.635333",
   "default": null,
   "depends_on": null,
   "description": null,
   "docstatus": 0,
   "dt": "Purchase Invoice",
   "fetch_from": null,
   "fetch_if_empty": 0,
   "fieldname": "location",
   "fieldtype": "Data",
   "hidden": 0,
   "idx": 164,
   "ignore_user_permissions": 0,
   "ignore_xss_filter": 0,
   "in_global_search": 0,
   "in_list_view": 0,
   "in_standard_filter": 0,
   "insert_after": "column_break_159",
   "label": "Location",
   "length": 0,
   "modified": "2021-10-21 15:57:24.146728",
   "modified_by": "Administrator",
   "name": "Purchase Invoice-location",
   "no_copy": 0,
   "options": null,
   "owner": "Administrator",
   "parent": null,
   "parentfield": null,
   "parenttype": null,
   "permlevel": 0,
   "precision": "",
   "print_hide": 0,
   "print_hide_if_no_value": 0,
   "print_width": null,
   "read_only": 1,
   "report_hide": 0,
   "reqd": 0,
   "search_index": 0,
   "translatable": 0,
   "unique": 0,
   "width": null
  },
  {
   "_assign": null,
   "_comments": null,
   "_liked_by": null,
   "_user_tags": null,
   "allow_in_quick_entry": 0,
   "allow_on_submit": 0,
   "bold": 0,
   "collapsible": 0,
   "collapsible_depends_on": null,
   "columns": 0,
   "creation": "2022-07-25 13:05:08.445454",
   "default": null,
   "depends_on": null,
   "description": null,
   "docstatus": 0,
   "dt": "Purchase Invoice",
   "fetch_from": null,
   "fetch_if_empty": 0,
   "fieldname": "location_description",
   "fieldtype": "Data",
   "hidden": 0,
   "idx": 165,
   "ignore_user_permissions": 0,
   "ignore_xss_filter": 0,
   "in_global_search": 0,
   "in_list_view": 0,
   "in_standard_filter": 0,
   "insert_after": "location",
   "label": "Location Description",
   "length": 0,
   "modified": "2021-10-21 15:57:25.341712",
   "modified_by": "Administrator",
   "name": "Purchase Invoice-location_description",
   "no_copy": 0,
   "options": null,
   "owner": "Administrator",
   "parent": null,
   "parentfield": null,
   "parenttype": null,
   "permlevel": 0,
   "precision": "",
   "print_hide": 0,
   "print_hide_if_no_value": 0,
   "print_width": null,
   "read_only": 1,
   "report_hide": 0,
   "reqd": 0,
   "search_index": 0,
   "translatable": 0,
   "unique": 0,
   "width": null
  },
  {
   "_assign": null,
   "_comments": null,
   "_liked_by": null,
   "_user_tags": null,
   "allow_in_quick_entry": 0,
   "allow_on_submit": 0,
   "bold": 0,
   "collapsible": 0,
   "collapsible_depends_on": null,
   "columns": 0,
   "creation": "2023-10-10 18:16:34.339607",
   "default": null,
   "depends_on": "eval:doc.rounded_total > 0 ",
   "description": null,
   "docstatus": 0,
   "dt": "Purchase Invoice",
   "fetch_from": null,
   "fetch_if_empty": 0,
   "fieldname": "customer_loan_details",
   "fieldtype": "Section Break",
   "hidden": 0,
   "idx": 120,
   "ignore_user_permissions": 0,
   "ignore_xss_filter": 0,
   "in_global_search": 0,
   "in_list_view": 0,
   "in_standard_filter": 0,
   "insert_after": "base_paid_amount",
   "label": "Customer Loan Details",
   "length": 0,
   "modified": "2023-10-10 18:16:34.339607",
   "modified_by": "Administrator",
   "name": "Purchase Invoice-customer_loan_details",
   "no_copy": 0,
   "options": null,
   "owner": "Administrator",
   "parent": null,
   "parentfield": null,
   "parenttype": null,
   "permlevel": 0,
   "precision": "",
   "print_hide": 0,
   "print_hide_if_no_value": 0,
   "print_width": null,
   "read_only": 0,
   "report_hide": 0,
   "reqd": 0,
   "search_index": 0,
   "translatable": 0,
   "unique": 0,
   "width": null
  },
  {
   "_assign": null,
   "_comments": null,
   "_liked_by": null,
   "_user_tags": null,
   "allow_in_quick_entry": 0,
   "allow_on_submit": 0,
   "bold": 0,
   "collapsible": 0,
   "collapsible_depends_on": null,
   "columns": 0,
   "creation": "2023-10-10 18:16:40.190181",
   "default": null,
   "depends_on": "eval:doc.rounded_total > 0 ",
   "description": null,
   "docstatus": 0,
   "dt": "Purchase Invoice",
   "fetch_from": null,
   "fetch_if_empty": 0,
   "fieldname": "customer_loan_deduction",
   "fieldtype": "Table",
   "hidden": 0,
   "idx": 121,
   "ignore_user_permissions": 0,
   "ignore_xss_filter": 0,
   "in_global_search": 0,
   "in_list_view": 0,
   "in_standard_filter": 0,
   "insert_after": "customer_loan_details",
   "label": "Customer Loan Deduction",
   "length": 0,
   "modified": "2023-10-10 18:16:40.190181",
   "modified_by": "Administrator",
   "name": "Purchase Invoice-customer_loan_deduction",
   "no_copy": 0,
   "options": "Customer Loan Details",
   "owner": "Administrator",
   "parent": null,
   "parentfield": null,
   "parenttype": null,
   "permlevel": 0,
   "precision": "",
   "print_hide": 0,
   "print_hide_if_no_value": 0,
   "print_width": null,
   "read_only": 0,
   "report_hide": 0,
   "reqd": 0,
   "search_index": 0,
   "translatable": 0,
   "unique": 0,
   "width": null
  }
 ],
 "custom_perms": [],
 "doctype": "Purchase Invoice",
 "property_setters": [
  {
   "_assign": null,
   "_comments": null,
   "_liked_by": null,
   "_user_tags": null,
   "creation": "2024-01-24 15:09:23.557440",
   "default_value": null,
   "doc_type": "Purchase Invoice",
   "docstatus": 0,
   "doctype_or_field": "DocField",
   "field_name": "status",
   "idx": 0,
   "modified": "2024-01-24 15:09:23.557440",
   "modified_by": "Administrator",
   "name": "Purchase Invoice-status-in_list_view",
   "owner": "Administrator",
   "parent": null,
   "parentfield": null,
   "parenttype": null,
   "property": "in_list_view",
   "property_type": "Check",
   "value": "1"
  },
  {
   "_assign": null,
   "_comments": null,
   "_liked_by": null,
   "_user_tags": null,
   "creation": "2024-01-02 13:22:20.852712",
   "default_value": null,
   "doc_type": "Purchase Invoice",
   "docstatus": 0,
   "doctype_or_field": "DocField",
   "field_name": "outstanding_amount",
   "idx": 0,
   "modified": "2024-01-02 13:22:20.852712",
   "modified_by": "Administrator",
   "name": "Purchase Invoice-outstanding_amount-precision",
   "owner": "Administrator",
   "parent": null,
   "parentfield": null,
   "parenttype": null,
   "property": "precision",
   "property_type": "Select",
   "value": "0"
  },
  {
   "_assign": null,
   "_comments": null,
   "_liked_by": null,
   "_user_tags": null,
   "creation": "2022-07-25 13:05:11.475395",
   "default_value": null,
   "doc_type": "Purchase Invoice",
   "docstatus": 0,
   "doctype_or_field": "DocField",
   "field_name": "naming_series",
   "idx": 0,
   "modified": "2023-12-01 16:23:02.516777",
   "modified_by": "zain.riaz@gourmetpakistan.com",
   "name": "Purchase Invoice-naming_series-default",
   "owner": "Administrator",
   "parent": null,
   "parentfield": null,
   "parenttype": null,
   "property": "default",
   "property_type": "Text",
   "value": ""
  },
  {
   "_assign": null,
   "_comments": null,
   "_liked_by": null,
   "_user_tags": null,
   "creation": "2023-11-25 16:18:08.540811",
   "default_value": null,
   "doc_type": "Purchase Invoice",
   "docstatus": 0,
   "doctype_or_field": "DocField",
   "field_name": "naming_series",
   "idx": 0,
   "modified": "2023-12-01 16:23:02.250239",
   "modified_by": "zain.riaz@gourmetpakistan.com",
   "name": "Purchase Invoice-naming_series-options",
   "owner": "Administrator",
   "parent": null,
   "parentfield": null,
   "parenttype": null,
   "property": "options",
   "property_type": "Text",
   "value": "\nPISM-.YY.-\nCPR-24-\nPIQAS-.YY.-"
  },
  {
   "_assign": null,
   "_comments": null,
   "_liked_by": null,
   "_user_tags": null,
   "creation": "2022-08-19 14:47:26.285411",
   "default_value": null,
   "doc_type": "Purchase Invoice",
   "docstatus": 0,
   "doctype_or_field": "DocField",
   "field_name": "payment_schedule",
   "idx": 0,
   "modified": "2022-08-19 14:47:26.285411",
   "modified_by": "Administrator",
   "name": "Purchase Invoice-payment_schedule-print_hide",
   "owner": "Administrator",
   "parent": null,
   "parentfield": null,
   "parenttype": null,
   "property": "print_hide",
   "property_type": "Check",
   "value": "1"
  },
  {
   "_assign": null,
   "_comments": null,
   "_liked_by": null,
   "_user_tags": null,
   "creation": "2022-08-19 14:47:25.924190",
   "default_value": null,
   "doc_type": "Purchase Invoice",
   "docstatus": 0,
   "doctype_or_field": "DocField",
   "field_name": "due_date",
   "idx": 0,
   "modified": "2022-08-19 14:47:25.924190",
   "modified_by": "Administrator",
   "name": "Purchase Invoice-due_date-print_hide",
   "owner": "Administrator",
   "parent": null,
   "parentfield": null,
   "parenttype": null,
   "property": "print_hide",
   "property_type": "Check",
   "value": "0"
  },
  {
   "_assign": null,
   "_comments": null,
   "_liked_by": null,
   "_user_tags": null,
   "creation": "2022-07-25 13:05:25.261074",
   "default_value": null,
   "doc_type": "Purchase Invoice",
   "docstatus": 0,
   "doctype_or_field": "DocField",
   "field_name": "scan_barcode",
   "idx": 0,
   "modified": "2021-12-01 16:09:33.672006",
   "modified_by": "Administrator",
   "name": "Purchase Invoice-scan_barcode-hidden",
   "owner": "Administrator",
   "parent": null,
   "parentfield": null,
   "parenttype": null,
   "property": "hidden",
   "property_type": "Check",
   "value": "0"
  },
  {
   "_assign": null,
   "_comments": null,
   "_liked_by": null,
   "_user_tags": null,
   "creation": "2022-07-25 13:05:24.810198",
   "default_value": null,
   "doc_type": "Purchase Invoice",
   "docstatus": 0,
   "doctype_or_field": "DocType",
   "field_name": null,
   "idx": 0,
   "modified": "2021-11-10 10:17:26.882547",
   "modified_by": "Administrator",
   "name": "Purchase Invoice-default_print_format",
   "owner": "Administrator",
   "parent": null,
   "parentfield": null,
   "parenttype": null,
   "property": "default_print_format",
   "property_type": "Data",
   "value": "Purchase Invoice"
  },
  {
   "_assign": null,
   "_comments": null,
   "_liked_by": null,
   "_user_tags": null,
   "creation": "2022-07-25 13:05:13.755684",
   "default_value": null,
   "doc_type": "Purchase Invoice",
   "docstatus": 0,
   "doctype_or_field": "DocField",
   "field_name": "in_words",
   "idx": 0,
   "modified": "2020-06-23 12:40:00.123511",
   "modified_by": "Administrator",
   "name": "Purchase Invoice-in_words-print_hide",
   "owner": "Administrator",
   "parent": null,
   "parentfield": null,
   "parenttype": null,
   "property": "print_hide",
   "property_type": "Check",
   "value": "0"
  },
  {
   "_assign": null,
   "_comments": null,
   "_liked_by": null,
   "_user_tags": null,
   "creation": "2022-07-25 13:05:13.712989",
   "default_value": null,
   "doc_type": "Purchase Invoice",
   "docstatus": 0,
   "doctype_or_field": "DocField",
   "field_name": "in_words",
   "idx": 0,
   "modified": "2020-06-23 12:39:59.847223",
   "modified_by": "Administrator",
   "name": "Purchase Invoice-in_words-hidden",
   "owner": "Administrator",
   "parent": null,
   "parentfield": null,
   "parenttype": null,
   "property": "hidden",
   "property_type": "Check",
   "value": "0"
  },
  {
   "_assign": null,
   "_comments": null,
   "_liked_by": null,
   "_user_tags": null,
   "creation": "2022-07-25 13:05:13.669317",
   "default_value": null,
   "doc_type": "Purchase Invoice",
   "docstatus": 0,
   "doctype_or_field": "DocField",
   "field_name": "rounded_total",
   "idx": 0,
   "modified": "2020-06-23 12:39:56.324567",
   "modified_by": "Administrator",
   "name": "Purchase Invoice-rounded_total-print_hide",
   "owner": "Administrator",
   "parent": null,
   "parentfield": null,
   "parenttype": null,
   "property": "print_hide",
   "property_type": "Check",
   "value": "0"
  },
  {
   "_assign": null,
   "_comments": null,
   "_liked_by": null,
   "_user_tags": null,
   "creation": "2022-07-25 13:05:13.619966",
   "default_value": null,
   "doc_type": "Purchase Invoice",
   "docstatus": 0,
   "doctype_or_field": "DocField",
   "field_name": "rounded_total",
   "idx": 0,
   "modified": "2020-06-23 12:39:56.071747",
   "modified_by": "Administrator",
   "name": "Purchase Invoice-rounded_total-hidden",
   "owner": "Administrator",
   "parent": null,
   "parentfield": null,
   "parenttype": null,
   "property": "hidden",
   "property_type": "Check",
   "value": "0"
  },
  {
   "_assign": null,
   "_comments": null,
   "_liked_by": null,
   "_user_tags": null,
   "creation": "2022-07-25 13:05:13.576658",
   "default_value": null,
   "doc_type": "Purchase Invoice",
   "docstatus": 0,
   "doctype_or_field": "DocField",
   "field_name": "base_rounded_total",
   "idx": 0,
   "modified": "2020-06-23 12:39:55.825416",
   "modified_by": "Administrator",
   "name": "Purchase Invoice-base_rounded_total-print_hide",
   "owner": "Administrator",
   "parent": null,
   "parentfield": null,
   "parenttype": null,
   "property": "print_hide",
   "property_type": "Check",
   "value": "1"
  },
  {
   "_assign": null,
   "_comments": null,
   "_liked_by": null,
   "_user_tags": null,
   "creation": "2022-07-25 13:05:13.503619",
   "default_value": null,
   "doc_type": "Purchase Invoice",
   "docstatus": 0,
   "doctype_or_field": "DocField",
   "field_name": "base_rounded_total",
   "idx": 0,
   "modified": "2020-06-23 12:39:55.538852",
   "modified_by": "Administrator",
   "name": "Purchase Invoice-base_rounded_total-hidden",
   "owner": "Administrator",
   "parent": null,
   "parentfield": null,
   "parenttype": null,
   "property": "hidden",
   "property_type": "Check",
   "value": "0"
  },
  {
   "_assign": null,
   "_comments": null,
   "_liked_by": null,
   "_user_tags": null,
   "creation": "2022-07-25 13:05:13.867597",
   "default_value": null,
   "doc_type": "Purchase Invoice",
   "docstatus": 0,
   "doctype_or_field": "DocField",
   "field_name": "cost_center",
   "idx": 0,
   "modified": "2020-05-19 13:25:12.005557",
   "modified_by": "Administrator",
   "name": "Purchase Invoice-cost_center-hidden",
   "owner": "Administrator",
   "parent": null,
   "parentfield": null,
   "parenttype": null,
   "property": "hidden",
   "property_type": "Check",
   "value": "1"
  }
 ],
 "sync_on_migrate": 1
}